{"nodes": [{"node_id": 1, "local_id": null, "owner_id": 0, "location": null, "executed": false, "min_domain": 60000.0, "max_domain": 101580.0}, {"node_id": 2, "local_id": null, "owner_id": 0, "location": null, "executed": false, "min_domain": -Infinity, "max_domain": Infinity}, {"node_id": 3, "local_id": null, "owner_id": 0, "location": null, "executed": false, "min_domain": -Infinity, "max_domain": Infinity}, {"node_id": 4, "local_id": null, "owner_id": 0, "location": null, "executed": false, "min_domain": -Infinity, "max_domain": Infinity}, {"node_id": 5, "local_id": null, "owner_id": 0, "location": null, "executed": false, "min_domain": -Infinity, "max_domain": Infinity}], "constraints": [{"first_node": 2, "second_node": 1, "distribution": {"name": "N_11.39_0.2278", "type": "Empirical"}, "min_duration": "-inf", "max_duration": "inf"}, {"first_node": 3, "second_node": 4, "min_duration": 2560.0, "max_duration": 10927.0}, {"first_node": 5, "second_node": 2, "min_duration": 840.0, "max_duration": 11405.999999999998}, {"first_node": 4, "second_node": 5, "distribution": {"name": "N_35.22_0.7044", "type": "Empirical"}, "min_duration": "-inf", "max_duration": "inf"}], "num_agents": 1}