{"nodes": [{"node_id": 1, "local_id": null, "owner_id": 0, "location": null, "executed": false, "min_domain": -Infinity, "max_domain": Infinity}, {"node_id": 2, "local_id": null, "owner_id": 0, "location": null, "executed": false, "min_domain": -Infinity, "max_domain": Infinity}, {"node_id": 3, "local_id": null, "owner_id": 0, "location": null, "executed": false, "min_domain": -Infinity, "max_domain": Infinity}, {"node_id": 4, "local_id": null, "owner_id": 0, "location": null, "executed": false, "min_domain": -Infinity, "max_domain": Infinity}, {"node_id": 5, "local_id": null, "owner_id": 0, "location": null, "executed": false, "min_domain": -Infinity, "max_domain": Infinity}, {"node_id": 6, "local_id": null, "owner_id": 0, "location": null, "executed": false, "min_domain": -Infinity, "max_domain": Infinity}, {"node_id": 7, "local_id": null, "owner_id": 0, "location": null, "executed": false, "min_domain": -Infinity, "max_domain": Infinity}, {"node_id": 8, "local_id": null, "owner_id": 0, "location": null, "executed": false, "min_domain": -Infinity, "max_domain": Infinity}, {"node_id": 9, "local_id": null, "owner_id": 0, "location": null, "executed": false, "min_domain": -Infinity, "max_domain": Infinity}, {"node_id": 10, "local_id": null, "owner_id": 0, "location": null, "executed": false, "min_domain": -Infinity, "max_domain": Infinity}, {"node_id": 11, "local_id": null, "owner_id": 0, "location": null, "executed": false, "min_domain": -Infinity, "max_domain": Infinity}, {"node_id": 12, "local_id": null, "owner_id": 0, "location": null, "executed": false, "min_domain": -Infinity, "max_domain": Infinity}, {"node_id": 13, "local_id": null, "owner_id": 0, "location": null, "executed": false, "min_domain": -Infinity, "max_domain": Infinity}, {"node_id": 14, "local_id": null, "owner_id": 0, "location": null, "executed": false, "min_domain": -Infinity, "max_domain": Infinity}, {"node_id": 15, "local_id": null, "owner_id": 0, "location": null, "executed": false, "min_domain": -Infinity, "max_domain": Infinity}, {"node_id": 16, "local_id": null, "owner_id": 0, "location": null, "executed": false, "min_domain": -Infinity, "max_domain": Infinity}, {"node_id": 17, "local_id": null, "owner_id": 0, "location": null, "executed": false, "min_domain": -Infinity, "max_domain": Infinity}, {"node_id": 18, "local_id": null, "owner_id": 0, "location": null, "executed": false, "min_domain": -Infinity, "max_domain": Infinity}, {"node_id": 19, "local_id": null, "owner_id": 0, "location": null, "executed": false, "min_domain": -Infinity, "max_domain": Infinity}, {"node_id": 20, "local_id": null, "owner_id": 0, "location": null, "executed": false, "min_domain": -Infinity, "max_domain": Infinity}, {"node_id": 21, "local_id": null, "owner_id": 0, "location": null, "executed": false, "min_domain": -Infinity, "max_domain": Infinity}, {"node_id": 22, "local_id": null, "owner_id": 0, "location": null, "executed": false, "min_domain": -Infinity, "max_domain": Infinity}, {"node_id": 23, "local_id": null, "owner_id": 0, "location": null, "executed": false, "min_domain": -Infinity, "max_domain": Infinity}, {"node_id": 24, "local_id": null, "owner_id": 0, "location": null, "executed": false, "min_domain": -Infinity, "max_domain": Infinity}, {"node_id": 25, "local_id": null, "owner_id": 0, "location": null, "executed": false, "min_domain": -Infinity, "max_domain": Infinity}, {"node_id": 26, "local_id": null, "owner_id": 0, "location": null, "executed": false, "min_domain": -Infinity, "max_domain": Infinity}, {"node_id": 27, "local_id": null, "owner_id": 0, "location": null, "executed": false, "min_domain": -Infinity, "max_domain": Infinity}, {"node_id": 28, "local_id": null, "owner_id": 0, "location": null, "executed": false, "min_domain": -Infinity, "max_domain": Infinity}, {"node_id": 29, "local_id": null, "owner_id": 0, "location": null, "executed": false, "min_domain": -Infinity, "max_domain": Infinity}, {"node_id": 30, "local_id": null, "owner_id": 0, "location": null, "executed": false, "min_domain": -Infinity, "max_domain": Infinity}, {"node_id": 31, "local_id": null, "owner_id": 0, "location": null, "executed": false, "min_domain": -Infinity, "max_domain": Infinity}, {"node_id": 32, "local_id": null, "owner_id": 0, "location": null, "executed": false, "min_domain": -Infinity, "max_domain": Infinity}, {"node_id": 33, "local_id": null, "owner_id": 0, "location": null, "executed": false, "min_domain": -Infinity, "max_domain": Infinity}, {"node_id": 34, "local_id": null, "owner_id": 0, "location": null, "executed": false, "min_domain": -Infinity, "max_domain": Infinity}, {"node_id": 35, "local_id": null, "owner_id": 0, "location": null, "executed": false, "min_domain": -Infinity, "max_domain": Infinity}, {"node_id": 36, "local_id": null, "owner_id": 0, "location": null, "executed": false, "min_domain": -Infinity, "max_domain": Infinity}, {"node_id": 37, "local_id": null, "owner_id": 0, "location": null, "executed": false, "min_domain": -Infinity, "max_domain": Infinity}, {"node_id": 38, "local_id": null, "owner_id": 0, "location": null, "executed": false, "min_domain": -Infinity, "max_domain": Infinity}, {"node_id": 39, "local_id": null, "owner_id": 0, "location": null, "executed": false, "min_domain": -Infinity, "max_domain": Infinity}, {"node_id": 40, "local_id": null, "owner_id": 0, "location": null, "executed": false, "min_domain": -Infinity, "max_domain": Infinity}, {"node_id": 41, "local_id": null, "owner_id": 0, "location": null, "executed": false, "min_domain": -Infinity, "max_domain": Infinity}, {"node_id": 42, "local_id": null, "owner_id": 0, "location": null, "executed": false, "min_domain": -Infinity, "max_domain": Infinity}, {"node_id": 43, "local_id": null, "owner_id": 0, "location": null, "executed": false, "min_domain": -Infinity, "max_domain": Infinity}, {"node_id": 44, "local_id": null, "owner_id": 0, "location": null, "executed": false, "min_domain": -Infinity, "max_domain": Infinity}, {"node_id": 45, "local_id": null, "owner_id": 0, "location": null, "executed": false, "min_domain": -Infinity, "max_domain": Infinity}, {"node_id": 46, "local_id": null, "owner_id": 0, "location": null, "executed": false, "min_domain": -Infinity, "max_domain": Infinity}, {"node_id": 47, "local_id": null, "owner_id": 0, "location": null, "executed": false, "min_domain": -Infinity, "max_domain": Infinity}, {"node_id": 48, "local_id": null, "owner_id": 0, "location": null, "executed": false, "min_domain": -Infinity, "max_domain": Infinity}, {"node_id": 49, "local_id": null, "owner_id": 0, "location": null, "executed": false, "min_domain": -Infinity, "max_domain": Infinity}, {"node_id": 50, "local_id": null, "owner_id": 0, "location": null, "executed": false, "min_domain": -Infinity, "max_domain": Infinity}, {"node_id": 51, "local_id": null, "owner_id": 0, "location": null, "executed": false, "min_domain": -Infinity, "max_domain": Infinity}, {"node_id": 52, "local_id": null, "owner_id": 0, "location": null, "executed": false, "min_domain": -Infinity, "max_domain": Infinity}, {"node_id": 53, "local_id": null, "owner_id": 0, "location": null, "executed": false, "min_domain": -Infinity, "max_domain": Infinity}, {"node_id": 54, "local_id": null, "owner_id": 0, "location": null, "executed": false, "min_domain": -Infinity, "max_domain": Infinity}, {"node_id": 55, "local_id": null, "owner_id": 0, "location": null, "executed": false, "min_domain": -Infinity, "max_domain": Infinity}, {"node_id": 56, "local_id": null, "owner_id": 0, "location": null, "executed": false, "min_domain": -Infinity, "max_domain": Infinity}, {"node_id": 57, "local_id": null, "owner_id": 0, "location": null, "executed": false, "min_domain": -Infinity, "max_domain": Infinity}, {"node_id": 58, "local_id": null, "owner_id": 0, "location": null, "executed": false, "min_domain": -Infinity, "max_domain": Infinity}, {"node_id": 59, "local_id": null, "owner_id": 0, "location": null, "executed": false, "min_domain": -Infinity, "max_domain": Infinity}, {"node_id": 60, "local_id": null, "owner_id": 0, "location": null, "executed": false, "min_domain": -Infinity, "max_domain": -0.0}, {"node_id": 61, "local_id": null, "owner_id": 0, "location": null, "executed": false, "min_domain": -Infinity, "max_domain": Infinity}, {"node_id": 62, "local_id": null, "owner_id": 0, "location": null, "executed": false, "min_domain": -Infinity, "max_domain": Infinity}, {"node_id": 63, "local_id": null, "owner_id": 0, "location": null, "executed": false, "min_domain": -Infinity, "max_domain": Infinity}, {"node_id": 64, "local_id": null, "owner_id": 0, "location": null, "executed": false, "min_domain": -Infinity, "max_domain": Infinity}, {"node_id": 65, "local_id": null, "owner_id": 0, "location": null, "executed": false, "min_domain": -Infinity, "max_domain": Infinity}, {"node_id": 66, "local_id": null, "owner_id": 0, "location": null, "executed": false, "min_domain": -Infinity, "max_domain": Infinity}, {"node_id": 67, "local_id": null, "owner_id": 0, "location": null, "executed": false, "min_domain": -Infinity, "max_domain": Infinity}, {"node_id": 68, "local_id": null, "owner_id": 0, "location": null, "executed": false, "min_domain": -Infinity, "max_domain": Infinity}, {"node_id": 69, "local_id": null, "owner_id": 0, "location": null, "executed": false, "min_domain": -Infinity, "max_domain": Infinity}, {"node_id": 70, "local_id": null, "owner_id": 0, "location": null, "executed": false, "min_domain": -Infinity, "max_domain": Infinity}, {"node_id": 71, "local_id": null, "owner_id": 0, "location": null, "executed": false, "min_domain": -Infinity, "max_domain": Infinity}, {"node_id": 72, "local_id": null, "owner_id": 0, "location": null, "executed": false, "min_domain": -Infinity, "max_domain": Infinity}, {"node_id": 73, "local_id": null, "owner_id": 0, "location": null, "executed": false, "min_domain": -Infinity, "max_domain": Infinity}, {"node_id": 74, "local_id": null, "owner_id": 0, "location": null, "executed": false, "min_domain": -Infinity, "max_domain": Infinity}, {"node_id": 75, "local_id": null, "owner_id": 0, "location": null, "executed": false, "min_domain": -Infinity, "max_domain": Infinity}, {"node_id": 76, "local_id": null, "owner_id": 0, "location": null, "executed": false, "min_domain": -Infinity, "max_domain": Infinity}, {"node_id": 77, "local_id": null, "owner_id": 0, "location": null, "executed": false, "min_domain": -Infinity, "max_domain": Infinity}, {"node_id": 78, "local_id": null, "owner_id": 0, "location": null, "executed": false, "min_domain": -Infinity, "max_domain": Infinity}, {"node_id": 79, "local_id": null, "owner_id": 0, "location": null, "executed": false, "min_domain": -Infinity, "max_domain": Infinity}, {"node_id": 80, "local_id": null, "owner_id": 0, "location": null, "executed": false, "min_domain": -Infinity, "max_domain": Infinity}, {"node_id": 81, "local_id": null, "owner_id": 0, "location": null, "executed": false, "min_domain": -Infinity, "max_domain": Infinity}, {"node_id": 82, "local_id": null, "owner_id": 0, "location": null, "executed": false, "min_domain": -Infinity, "max_domain": Infinity}, {"node_id": 83, "local_id": null, "owner_id": 0, "location": null, "executed": false, "min_domain": -Infinity, "max_domain": Infinity}, {"node_id": 84, "local_id": null, "owner_id": 0, "location": null, "executed": false, "min_domain": -Infinity, "max_domain": Infinity}, {"node_id": 85, "local_id": null, "owner_id": 0, "location": null, "executed": false, "min_domain": -Infinity, "max_domain": Infinity}, {"node_id": 86, "local_id": null, "owner_id": 0, "location": null, "executed": false, "min_domain": -Infinity, "max_domain": Infinity}, {"node_id": 87, "local_id": null, "owner_id": 0, "location": null, "executed": false, "min_domain": -Infinity, "max_domain": Infinity}, {"node_id": 88, "local_id": null, "owner_id": 0, "location": null, "executed": false, "min_domain": -Infinity, "max_domain": Infinity}, {"node_id": 89, "local_id": null, "owner_id": 0, "location": null, "executed": false, "min_domain": -Infinity, "max_domain": Infinity}, {"node_id": 90, "local_id": null, "owner_id": 0, "location": null, "executed": false, "min_domain": -Infinity, "max_domain": Infinity}, {"node_id": 91, "local_id": null, "owner_id": 0, "location": null, "executed": false, "min_domain": -Infinity, "max_domain": Infinity}, {"node_id": 92, "local_id": null, "owner_id": 0, "location": null, "executed": false, "min_domain": -Infinity, "max_domain": Infinity}, {"node_id": 93, "local_id": null, "owner_id": 0, "location": null, "executed": false, "min_domain": -Infinity, "max_domain": Infinity}, {"node_id": 94, "local_id": null, "owner_id": 0, "location": null, "executed": false, "min_domain": -Infinity, "max_domain": Infinity}, {"node_id": 95, "local_id": null, "owner_id": 0, "location": null, "executed": false, "min_domain": -Infinity, "max_domain": Infinity}, {"node_id": 96, "local_id": null, "owner_id": 0, "location": null, "executed": false, "min_domain": -Infinity, "max_domain": Infinity}, {"node_id": 97, "local_id": null, "owner_id": 0, "location": null, "executed": false, "min_domain": -Infinity, "max_domain": Infinity}, {"node_id": 98, "local_id": null, "owner_id": 0, "location": null, "executed": false, "min_domain": -Infinity, "max_domain": Infinity}, {"node_id": 99, "local_id": null, "owner_id": 0, "location": null, "executed": false, "min_domain": -Infinity, "max_domain": Infinity}, {"node_id": 100, "local_id": null, "owner_id": 0, "location": null, "executed": false, "min_domain": -Infinity, "max_domain": Infinity}, {"node_id": 101, "local_id": null, "owner_id": 0, "location": null, "executed": false, "min_domain": -Infinity, "max_domain": Infinity}, {"node_id": 102, "local_id": null, "owner_id": 0, "location": null, "executed": false, "min_domain": -Infinity, "max_domain": Infinity}, {"node_id": 103, "local_id": null, "owner_id": 0, "location": null, "executed": false, "min_domain": -Infinity, "max_domain": Infinity}, {"node_id": 104, "local_id": null, "owner_id": 0, "location": null, "executed": false, "min_domain": -Infinity, "max_domain": Infinity}, {"node_id": 105, "local_id": null, "owner_id": 0, "location": null, "executed": false, "min_domain": -Infinity, "max_domain": Infinity}, {"node_id": 106, "local_id": null, "owner_id": 0, "location": null, "executed": false, "min_domain": -Infinity, "max_domain": Infinity}, {"node_id": 107, "local_id": null, "owner_id": 0, "location": null, "executed": false, "min_domain": -Infinity, "max_domain": Infinity}, {"node_id": 108, "local_id": null, "owner_id": 0, "location": null, "executed": false, "min_domain": -Infinity, "max_domain": Infinity}, {"node_id": 109, "local_id": null, "owner_id": 0, "location": null, "executed": false, "min_domain": -Infinity, "max_domain": Infinity}, {"node_id": 110, "local_id": null, "owner_id": 0, "location": null, "executed": false, "min_domain": -Infinity, "max_domain": Infinity}, {"node_id": 111, "local_id": null, "owner_id": 0, "location": null, "executed": false, "min_domain": -Infinity, "max_domain": Infinity}, {"node_id": 112, "local_id": null, "owner_id": 0, "location": null, "executed": false, "min_domain": -Infinity, "max_domain": Infinity}, {"node_id": 113, "local_id": null, "owner_id": 0, "location": null, "executed": false, "min_domain": -Infinity, "max_domain": Infinity}, {"node_id": 114, "local_id": null, "owner_id": 0, "location": null, "executed": false, "min_domain": -Infinity, "max_domain": Infinity}, {"node_id": 115, "local_id": null, "owner_id": 0, "location": null, "executed": false, "min_domain": -Infinity, "max_domain": Infinity}, {"node_id": 116, "local_id": null, "owner_id": 0, "location": null, "executed": false, "min_domain": -Infinity, "max_domain": Infinity}, {"node_id": 117, "local_id": null, "owner_id": 0, "location": null, "executed": false, "min_domain": -Infinity, "max_domain": Infinity}, {"node_id": 118, "local_id": null, "owner_id": 0, "location": null, "executed": false, "min_domain": -Infinity, "max_domain": Infinity}, {"node_id": 119, "local_id": null, "owner_id": 0, "location": null, "executed": false, "min_domain": -Infinity, "max_domain": Infinity}, {"node_id": 120, "local_id": null, "owner_id": 0, "location": null, "executed": false, "min_domain": -Infinity, "max_domain": Infinity}, {"node_id": 121, "local_id": null, "owner_id": 0, "location": null, "executed": false, "min_domain": -Infinity, "max_domain": Infinity}, {"node_id": 122, "local_id": null, "owner_id": 0, "location": null, "executed": false, "min_domain": -Infinity, "max_domain": Infinity}, {"node_id": 123, "local_id": null, "owner_id": 0, "location": null, "executed": false, "min_domain": -Infinity, "max_domain": Infinity}, {"node_id": 124, "local_id": null, "owner_id": 0, "location": null, "executed": false, "min_domain": -Infinity, "max_domain": Infinity}, {"node_id": 125, "local_id": null, "owner_id": 0, "location": null, "executed": false, "min_domain": -Infinity, "max_domain": Infinity}, {"node_id": 126, "local_id": null, "owner_id": 0, "location": null, "executed": false, "min_domain": -Infinity, "max_domain": Infinity}, {"node_id": 127, "local_id": null, "owner_id": 0, "location": null, "executed": false, "min_domain": -Infinity, "max_domain": Infinity}, {"node_id": 128, "local_id": null, "owner_id": 0, "location": null, "executed": false, "min_domain": -Infinity, "max_domain": Infinity}, {"node_id": 129, "local_id": null, "owner_id": 0, "location": null, "executed": false, "min_domain": -Infinity, "max_domain": Infinity}, {"node_id": 130, "local_id": null, "owner_id": 0, "location": null, "executed": false, "min_domain": -Infinity, "max_domain": Infinity}, {"node_id": 131, "local_id": null, "owner_id": 0, "location": null, "executed": false, "min_domain": -Infinity, "max_domain": Infinity}, {"node_id": 132, "local_id": null, "owner_id": 0, "location": null, "executed": false, "min_domain": -Infinity, "max_domain": Infinity}, {"node_id": 133, "local_id": null, "owner_id": 0, "location": null, "executed": false, "min_domain": -Infinity, "max_domain": Infinity}, {"node_id": 134, "local_id": null, "owner_id": 0, "location": null, "executed": false, "min_domain": -Infinity, "max_domain": Infinity}, {"node_id": 135, "local_id": null, "owner_id": 0, "location": null, "executed": false, "min_domain": -Infinity, "max_domain": Infinity}, {"node_id": 136, "local_id": null, "owner_id": 0, "location": null, "executed": false, "min_domain": -Infinity, "max_domain": Infinity}, {"node_id": 137, "local_id": null, "owner_id": 0, "location": null, "executed": false, "min_domain": -Infinity, "max_domain": Infinity}, {"node_id": 138, "local_id": null, "owner_id": 0, "location": null, "executed": false, "min_domain": -Infinity, "max_domain": Infinity}, {"node_id": 139, "local_id": null, "owner_id": 0, "location": null, "executed": false, "min_domain": -Infinity, "max_domain": Infinity}, {"node_id": 140, "local_id": null, "owner_id": 0, "location": null, "executed": false, "min_domain": -Infinity, "max_domain": Infinity}, {"node_id": 141, "local_id": null, "owner_id": 0, "location": null, "executed": false, "min_domain": -Infinity, "max_domain": Infinity}, {"node_id": 142, "local_id": null, "owner_id": 0, "location": null, "executed": false, "min_domain": -Infinity, "max_domain": Infinity}, {"node_id": 143, "local_id": null, "owner_id": 0, "location": null, "executed": false, "min_domain": -Infinity, "max_domain": Infinity}, {"node_id": 144, "local_id": null, "owner_id": 0, "location": null, "executed": false, "min_domain": -Infinity, "max_domain": Infinity}, {"node_id": 145, "local_id": null, "owner_id": 0, "location": null, "executed": false, "min_domain": -Infinity, "max_domain": Infinity}, {"node_id": 146, "local_id": null, "owner_id": 0, "location": null, "executed": false, "min_domain": -Infinity, "max_domain": Infinity}, {"node_id": 147, "local_id": null, "owner_id": 0, "location": null, "executed": false, "min_domain": -Infinity, "max_domain": Infinity}, {"node_id": 148, "local_id": null, "owner_id": 0, "location": null, "executed": false, "min_domain": -Infinity, "max_domain": Infinity}, {"node_id": 149, "local_id": null, "owner_id": 0, "location": null, "executed": false, "min_domain": -Infinity, "max_domain": Infinity}, {"node_id": 150, "local_id": null, "owner_id": 0, "location": null, "executed": false, "min_domain": -Infinity, "max_domain": Infinity}, {"node_id": 151, "local_id": null, "owner_id": 0, "location": null, "executed": false, "min_domain": -Infinity, "max_domain": Infinity}, {"node_id": 152, "local_id": null, "owner_id": 0, "location": null, "executed": false, "min_domain": -Infinity, "max_domain": Infinity}, {"node_id": 153, "local_id": null, "owner_id": 0, "location": null, "executed": false, "min_domain": -Infinity, "max_domain": Infinity}, {"node_id": 154, "local_id": null, "owner_id": 0, "location": null, "executed": false, "min_domain": -Infinity, "max_domain": Infinity}, {"node_id": 155, "local_id": null, "owner_id": 0, "location": null, "executed": false, "min_domain": -Infinity, "max_domain": Infinity}, {"node_id": 156, "local_id": null, "owner_id": 0, "location": null, "executed": false, "min_domain": -Infinity, "max_domain": Infinity}, {"node_id": 157, "local_id": null, "owner_id": 0, "location": null, "executed": false, "min_domain": -Infinity, "max_domain": Infinity}, {"node_id": 158, "local_id": null, "owner_id": 0, "location": null, "executed": false, "min_domain": -Infinity, "max_domain": Infinity}, {"node_id": 159, "local_id": null, "owner_id": 0, "location": null, "executed": false, "min_domain": -Infinity, "max_domain": Infinity}, {"node_id": 160, "local_id": null, "owner_id": 0, "location": null, "executed": false, "min_domain": -Infinity, "max_domain": Infinity}, {"node_id": 161, "local_id": null, "owner_id": 0, "location": null, "executed": false, "min_domain": -Infinity, "max_domain": Infinity}, {"node_id": 162, "local_id": null, "owner_id": 0, "location": null, "executed": false, "min_domain": -Infinity, "max_domain": Infinity}, {"node_id": 163, "local_id": null, "owner_id": 0, "location": null, "executed": false, "min_domain": -Infinity, "max_domain": Infinity}, {"node_id": 164, "local_id": null, "owner_id": 0, "location": null, "executed": false, "min_domain": -Infinity, "max_domain": Infinity}, {"node_id": 165, "local_id": null, "owner_id": 0, "location": null, "executed": false, "min_domain": -Infinity, "max_domain": Infinity}, {"node_id": 166, "local_id": null, "owner_id": 0, "location": null, "executed": false, "min_domain": -Infinity, "max_domain": Infinity}, {"node_id": 167, "local_id": null, "owner_id": 0, "location": null, "executed": false, "min_domain": -Infinity, "max_domain": Infinity}, {"node_id": 168, "local_id": null, "owner_id": 0, "location": null, "executed": false, "min_domain": -Infinity, "max_domain": Infinity}, {"node_id": 169, "local_id": null, "owner_id": 0, "location": null, "executed": false, "min_domain": -Infinity, "max_domain": Infinity}, {"node_id": 170, "local_id": null, "owner_id": 0, "location": null, "executed": false, "min_domain": -Infinity, "max_domain": Infinity}, {"node_id": 171, "local_id": null, "owner_id": 0, "location": null, "executed": false, "min_domain": -Infinity, "max_domain": Infinity}, {"node_id": 172, "local_id": null, "owner_id": 0, "location": null, "executed": false, "min_domain": -Infinity, "max_domain": Infinity}, {"node_id": 173, "local_id": null, "owner_id": 0, "location": null, "executed": false, "min_domain": -Infinity, "max_domain": Infinity}, {"node_id": 174, "local_id": null, "owner_id": 0, "location": null, "executed": false, "min_domain": -Infinity, "max_domain": Infinity}, {"node_id": 175, "local_id": null, "owner_id": 0, "location": null, "executed": false, "min_domain": -Infinity, "max_domain": Infinity}, {"node_id": 176, "local_id": null, "owner_id": 0, "location": null, "executed": false, "min_domain": -Infinity, "max_domain": Infinity}, {"node_id": 177, "local_id": null, "owner_id": 0, "location": null, "executed": false, "min_domain": -Infinity, "max_domain": Infinity}, {"node_id": 178, "local_id": null, "owner_id": 0, "location": null, "executed": false, "min_domain": -Infinity, "max_domain": Infinity}, {"node_id": 179, "local_id": null, "owner_id": 0, "location": null, "executed": false, "min_domain": -Infinity, "max_domain": Infinity}, {"node_id": 180, "local_id": null, "owner_id": 0, "location": null, "executed": false, "min_domain": -Infinity, "max_domain": Infinity}, {"node_id": 181, "local_id": null, "owner_id": 0, "location": null, "executed": false, "min_domain": -Infinity, "max_domain": Infinity}, {"node_id": 182, "local_id": null, "owner_id": 0, "location": null, "executed": false, "min_domain": -Infinity, "max_domain": Infinity}, {"node_id": 183, "local_id": null, "owner_id": 0, "location": null, "executed": false, "min_domain": -Infinity, "max_domain": Infinity}, {"node_id": 184, "local_id": null, "owner_id": 0, "location": null, "executed": false, "min_domain": -Infinity, "max_domain": Infinity}, {"node_id": 185, "local_id": null, "owner_id": 0, "location": null, "executed": false, "min_domain": -Infinity, "max_domain": Infinity}, {"node_id": 186, "local_id": null, "owner_id": 0, "location": null, "executed": false, "min_domain": -Infinity, "max_domain": Infinity}, {"node_id": 187, "local_id": null, "owner_id": 0, "location": null, "executed": false, "min_domain": -Infinity, "max_domain": Infinity}, {"node_id": 188, "local_id": null, "owner_id": 0, "location": null, "executed": false, "min_domain": -Infinity, "max_domain": Infinity}, {"node_id": 189, "local_id": null, "owner_id": 0, "location": null, "executed": false, "min_domain": -Infinity, "max_domain": Infinity}, {"node_id": 190, "local_id": null, "owner_id": 0, "location": null, "executed": false, "min_domain": -Infinity, "max_domain": Infinity}, {"node_id": 191, "local_id": null, "owner_id": 0, "location": null, "executed": false, "min_domain": -Infinity, "max_domain": Infinity}, {"node_id": 192, "local_id": null, "owner_id": 0, "location": null, "executed": false, "min_domain": -Infinity, "max_domain": Infinity}, {"node_id": 193, "local_id": null, "owner_id": 0, "location": null, "executed": false, "min_domain": -Infinity, "max_domain": Infinity}, {"node_id": 194, "local_id": null, "owner_id": 0, "location": null, "executed": false, "min_domain": -Infinity, "max_domain": Infinity}, {"node_id": 195, "local_id": null, "owner_id": 0, "location": null, "executed": false, "min_domain": -Infinity, "max_domain": Infinity}, {"node_id": 196, "local_id": null, "owner_id": 0, "location": null, "executed": false, "min_domain": -Infinity, "max_domain": Infinity}, {"node_id": 197, "local_id": null, "owner_id": 0, "location": null, "executed": false, "min_domain": -Infinity, "max_domain": Infinity}, {"node_id": 198, "local_id": null, "owner_id": 0, "location": null, "executed": false, "min_domain": -Infinity, "max_domain": Infinity}, {"node_id": 199, "local_id": null, "owner_id": 0, "location": null, "executed": false, "min_domain": -Infinity, "max_domain": Infinity}, {"node_id": 200, "local_id": null, "owner_id": 0, "location": null, "executed": false, "min_domain": -Infinity, "max_domain": Infinity}, {"node_id": 201, "local_id": null, "owner_id": 0, "location": null, "executed": false, "min_domain": -Infinity, "max_domain": Infinity}, {"node_id": 202, "local_id": null, "owner_id": 0, "location": null, "executed": false, "min_domain": -Infinity, "max_domain": Infinity}, {"node_id": 203, "local_id": null, "owner_id": 0, "location": null, "executed": false, "min_domain": -Infinity, "max_domain": Infinity}, {"node_id": 204, "local_id": null, "owner_id": 0, "location": null, "executed": false, "min_domain": -Infinity, "max_domain": Infinity}, {"node_id": 205, "local_id": null, "owner_id": 0, "location": null, "executed": false, "min_domain": -Infinity, "max_domain": Infinity}, {"node_id": 206, "local_id": null, "owner_id": 0, "location": null, "executed": false, "min_domain": -Infinity, "max_domain": Infinity}, {"node_id": 207, "local_id": null, "owner_id": 0, "location": null, "executed": false, "min_domain": -Infinity, "max_domain": Infinity}, {"node_id": 208, "local_id": null, "owner_id": 0, "location": null, "executed": false, "min_domain": -Infinity, "max_domain": Infinity}, {"node_id": 209, "local_id": null, "owner_id": 0, "location": null, "executed": false, "min_domain": -Infinity, "max_domain": Infinity}, {"node_id": 210, "local_id": null, "owner_id": 0, "location": null, "executed": false, "min_domain": -Infinity, "max_domain": Infinity}, {"node_id": 211, "local_id": null, "owner_id": 0, "location": null, "executed": false, "min_domain": -Infinity, "max_domain": Infinity}, {"node_id": 212, "local_id": null, "owner_id": 0, "location": null, "executed": false, "min_domain": -Infinity, "max_domain": Infinity}, {"node_id": 213, "local_id": null, "owner_id": 0, "location": null, "executed": false, "min_domain": -Infinity, "max_domain": Infinity}, {"node_id": 214, "local_id": null, "owner_id": 0, "location": null, "executed": false, "min_domain": -Infinity, "max_domain": Infinity}, {"node_id": 215, "local_id": null, "owner_id": 0, "location": null, "executed": false, "min_domain": -Infinity, "max_domain": Infinity}, {"node_id": 216, "local_id": null, "owner_id": 0, "location": null, "executed": false, "min_domain": -Infinity, "max_domain": Infinity}, {"node_id": 217, "local_id": null, "owner_id": 0, "location": null, "executed": false, "min_domain": -Infinity, "max_domain": Infinity}, {"node_id": 218, "local_id": null, "owner_id": 0, "location": null, "executed": false, "min_domain": -Infinity, "max_domain": Infinity}, {"node_id": 219, "local_id": null, "owner_id": 0, "location": null, "executed": false, "min_domain": -Infinity, "max_domain": Infinity}, {"node_id": 220, "local_id": null, "owner_id": 0, "location": null, "executed": false, "min_domain": -Infinity, "max_domain": Infinity}, {"node_id": 221, "local_id": null, "owner_id": 0, "location": null, "executed": false, "min_domain": -Infinity, "max_domain": Infinity}, {"node_id": 222, "local_id": null, "owner_id": 0, "location": null, "executed": false, "min_domain": -Infinity, "max_domain": Infinity}, {"node_id": 223, "local_id": null, "owner_id": 0, "location": null, "executed": false, "min_domain": -Infinity, "max_domain": Infinity}, {"node_id": 224, "local_id": null, "owner_id": 0, "location": null, "executed": false, "min_domain": -Infinity, "max_domain": Infinity}, {"node_id": 225, "local_id": null, "owner_id": 0, "location": null, "executed": false, "min_domain": -Infinity, "max_domain": Infinity}, {"node_id": 226, "local_id": null, "owner_id": 0, "location": null, "executed": false, "min_domain": -Infinity, "max_domain": Infinity}, {"node_id": 227, "local_id": null, "owner_id": 0, "location": null, "executed": false, "min_domain": -Infinity, "max_domain": Infinity}, {"node_id": 228, "local_id": null, "owner_id": 0, "location": null, "executed": false, "min_domain": -Infinity, "max_domain": Infinity}, {"node_id": 229, "local_id": null, "owner_id": 0, "location": null, "executed": false, "min_domain": -Infinity, "max_domain": Infinity}, {"node_id": 230, "local_id": null, "owner_id": 0, "location": null, "executed": false, "min_domain": -Infinity, "max_domain": Infinity}, {"node_id": 231, "local_id": null, "owner_id": 0, "location": null, "executed": false, "min_domain": -Infinity, "max_domain": Infinity}, {"node_id": 232, "local_id": null, "owner_id": 0, "location": null, "executed": false, "min_domain": -Infinity, "max_domain": Infinity}, {"node_id": 233, "local_id": null, "owner_id": 0, "location": null, "executed": false, "min_domain": -Infinity, "max_domain": Infinity}, {"node_id": 234, "local_id": null, "owner_id": 0, "location": null, "executed": false, "min_domain": -Infinity, "max_domain": Infinity}, {"node_id": 235, "local_id": null, "owner_id": 0, "location": null, "executed": false, "min_domain": -Infinity, "max_domain": Infinity}, {"node_id": 236, "local_id": null, "owner_id": 0, "location": null, "executed": false, "min_domain": -Infinity, "max_domain": Infinity}, {"node_id": 237, "local_id": null, "owner_id": 0, "location": null, "executed": false, "min_domain": -Infinity, "max_domain": Infinity}, {"node_id": 238, "local_id": null, "owner_id": 0, "location": null, "executed": false, "min_domain": -Infinity, "max_domain": Infinity}, {"node_id": 239, "local_id": null, "owner_id": 0, "location": null, "executed": false, "min_domain": -Infinity, "max_domain": Infinity}, {"node_id": 240, "local_id": null, "owner_id": 0, "location": null, "executed": false, "min_domain": -Infinity, "max_domain": Infinity}, {"node_id": 241, "local_id": null, "owner_id": 0, "location": null, "executed": false, "min_domain": -Infinity, "max_domain": Infinity}, {"node_id": 242, "local_id": null, "owner_id": 0, "location": null, "executed": false, "min_domain": -Infinity, "max_domain": Infinity}, {"node_id": 243, "local_id": null, "owner_id": 0, "location": null, "executed": false, "min_domain": -Infinity, "max_domain": Infinity}, {"node_id": 244, "local_id": null, "owner_id": 0, "location": null, "executed": false, "min_domain": -Infinity, "max_domain": Infinity}, {"node_id": 245, "local_id": null, "owner_id": 0, "location": null, "executed": false, "min_domain": -Infinity, "max_domain": Infinity}, {"node_id": 246, "local_id": null, "owner_id": 0, "location": null, "executed": false, "min_domain": -Infinity, "max_domain": Infinity}, {"node_id": 247, "local_id": null, "owner_id": 0, "location": null, "executed": false, "min_domain": -Infinity, "max_domain": Infinity}, {"node_id": 248, "local_id": null, "owner_id": 0, "location": null, "executed": false, "min_domain": -Infinity, "max_domain": Infinity}, {"node_id": 249, "local_id": null, "owner_id": 0, "location": null, "executed": false, "min_domain": -Infinity, "max_domain": Infinity}, {"node_id": 250, "local_id": null, "owner_id": 0, "location": null, "executed": false, "min_domain": -Infinity, "max_domain": Infinity}, {"node_id": 251, "local_id": null, "owner_id": 0, "location": null, "executed": false, "min_domain": -Infinity, "max_domain": Infinity}, {"node_id": 252, "local_id": null, "owner_id": 0, "location": null, "executed": false, "min_domain": -Infinity, "max_domain": Infinity}, {"node_id": 253, "local_id": null, "owner_id": 0, "location": null, "executed": false, "min_domain": -Infinity, "max_domain": Infinity}, {"node_id": 254, "local_id": null, "owner_id": 0, "location": null, "executed": false, "min_domain": -Infinity, "max_domain": Infinity}, {"node_id": 255, "local_id": null, "owner_id": 0, "location": null, "executed": false, "min_domain": -Infinity, "max_domain": Infinity}, {"node_id": 256, "local_id": null, "owner_id": 0, "location": null, "executed": false, "min_domain": -Infinity, "max_domain": Infinity}, {"node_id": 257, "local_id": null, "owner_id": 0, "location": null, "executed": false, "min_domain": -Infinity, "max_domain": Infinity}, {"node_id": 258, "local_id": null, "owner_id": 0, "location": null, "executed": false, "min_domain": -Infinity, "max_domain": Infinity}, {"node_id": 259, "local_id": null, "owner_id": 0, "location": null, "executed": false, "min_domain": -Infinity, "max_domain": Infinity}, {"node_id": 260, "local_id": null, "owner_id": 0, "location": null, "executed": false, "min_domain": -Infinity, "max_domain": Infinity}, {"node_id": 261, "local_id": null, "owner_id": 0, "location": null, "executed": false, "min_domain": -Infinity, "max_domain": Infinity}, {"node_id": 262, "local_id": null, "owner_id": 0, "location": null, "executed": false, "min_domain": -Infinity, "max_domain": Infinity}, {"node_id": 263, "local_id": null, "owner_id": 0, "location": null, "executed": false, "min_domain": -Infinity, "max_domain": Infinity}, {"node_id": 264, "local_id": null, "owner_id": 0, "location": null, "executed": false, "min_domain": -Infinity, "max_domain": Infinity}, {"node_id": 265, "local_id": null, "owner_id": 0, "location": null, "executed": false, "min_domain": -Infinity, "max_domain": Infinity}, {"node_id": 266, "local_id": null, "owner_id": 0, "location": null, "executed": false, "min_domain": -Infinity, "max_domain": Infinity}, {"node_id": 267, "local_id": null, "owner_id": 0, "location": null, "executed": false, "min_domain": -Infinity, "max_domain": Infinity}, {"node_id": 268, "local_id": null, "owner_id": 0, "location": null, "executed": false, "min_domain": -Infinity, "max_domain": Infinity}, {"node_id": 269, "local_id": null, "owner_id": 0, "location": null, "executed": false, "min_domain": -Infinity, "max_domain": Infinity}, {"node_id": 270, "local_id": null, "owner_id": 0, "location": null, "executed": false, "min_domain": -Infinity, "max_domain": Infinity}, {"node_id": 271, "local_id": null, "owner_id": 0, "location": null, "executed": false, "min_domain": -Infinity, "max_domain": Infinity}, {"node_id": 272, "local_id": null, "owner_id": 0, "location": null, "executed": false, "min_domain": -Infinity, "max_domain": Infinity}, {"node_id": 273, "local_id": null, "owner_id": 0, "location": null, "executed": false, "min_domain": -Infinity, "max_domain": Infinity}, {"node_id": 274, "local_id": null, "owner_id": 0, "location": null, "executed": false, "min_domain": -Infinity, "max_domain": Infinity}, {"node_id": 275, "local_id": null, "owner_id": 0, "location": null, "executed": false, "min_domain": -Infinity, "max_domain": Infinity}, {"node_id": 276, "local_id": null, "owner_id": 0, "location": null, "executed": false, "min_domain": -Infinity, "max_domain": Infinity}, {"node_id": 277, "local_id": null, "owner_id": 0, "location": null, "executed": false, "min_domain": -Infinity, "max_domain": Infinity}, {"node_id": 278, "local_id": null, "owner_id": 0, "location": null, "executed": false, "min_domain": -Infinity, "max_domain": Infinity}, {"node_id": 279, "local_id": null, "owner_id": 0, "location": null, "executed": false, "min_domain": -Infinity, "max_domain": Infinity}, {"node_id": 280, "local_id": null, "owner_id": 0, "location": null, "executed": false, "min_domain": -Infinity, "max_domain": Infinity}, {"node_id": 281, "local_id": null, "owner_id": 0, "location": null, "executed": false, "min_domain": -Infinity, "max_domain": Infinity}, {"node_id": 282, "local_id": null, "owner_id": 0, "location": null, "executed": false, "min_domain": -Infinity, "max_domain": Infinity}, {"node_id": 283, "local_id": null, "owner_id": 0, "location": null, "executed": false, "min_domain": -Infinity, "max_domain": Infinity}, {"node_id": 284, "local_id": null, "owner_id": 0, "location": null, "executed": false, "min_domain": -Infinity, "max_domain": Infinity}, {"node_id": 285, "local_id": null, "owner_id": 0, "location": null, "executed": false, "min_domain": -Infinity, "max_domain": Infinity}, {"node_id": 286, "local_id": null, "owner_id": 0, "location": null, "executed": false, "min_domain": -Infinity, "max_domain": Infinity}, {"node_id": 287, "local_id": null, "owner_id": 0, "location": null, "executed": false, "min_domain": -Infinity, "max_domain": Infinity}, {"node_id": 288, "local_id": null, "owner_id": 0, "location": null, "executed": false, "min_domain": -Infinity, "max_domain": Infinity}, {"node_id": 289, "local_id": null, "owner_id": 0, "location": null, "executed": false, "min_domain": -Infinity, "max_domain": Infinity}, {"node_id": 290, "local_id": null, "owner_id": 0, "location": null, "executed": false, "min_domain": -Infinity, "max_domain": Infinity}, {"node_id": 291, "local_id": null, "owner_id": 0, "location": null, "executed": false, "min_domain": -Infinity, "max_domain": Infinity}, {"node_id": 292, "local_id": null, "owner_id": 0, "location": null, "executed": false, "min_domain": -Infinity, "max_domain": Infinity}, {"node_id": 293, "local_id": null, "owner_id": 0, "location": null, "executed": false, "min_domain": -Infinity, "max_domain": Infinity}, {"node_id": 294, "local_id": null, "owner_id": 0, "location": null, "executed": false, "min_domain": -Infinity, "max_domain": Infinity}, {"node_id": 295, "local_id": null, "owner_id": 0, "location": null, "executed": false, "min_domain": -Infinity, "max_domain": Infinity}, {"node_id": 296, "local_id": null, "owner_id": 0, "location": null, "executed": false, "min_domain": -Infinity, "max_domain": Infinity}, {"node_id": 297, "local_id": null, "owner_id": 0, "location": null, "executed": false, "min_domain": -Infinity, "max_domain": Infinity}, {"node_id": 298, "local_id": null, "owner_id": 0, "location": null, "executed": false, "min_domain": -Infinity, "max_domain": Infinity}, {"node_id": 299, "local_id": null, "owner_id": 0, "location": null, "executed": false, "min_domain": -Infinity, "max_domain": Infinity}, {"node_id": 300, "local_id": null, "owner_id": 0, "location": null, "executed": false, "min_domain": -Infinity, "max_domain": Infinity}, {"node_id": 301, "local_id": null, "owner_id": 0, "location": null, "executed": false, "min_domain": -Infinity, "max_domain": Infinity}, {"node_id": 302, "local_id": null, "owner_id": 0, "location": null, "executed": false, "min_domain": -Infinity, "max_domain": Infinity}, {"node_id": 303, "local_id": null, "owner_id": 0, "location": null, "executed": false, "min_domain": -Infinity, "max_domain": Infinity}, {"node_id": 304, "local_id": null, "owner_id": 0, "location": null, "executed": false, "min_domain": -Infinity, "max_domain": Infinity}, {"node_id": 305, "local_id": null, "owner_id": 0, "location": null, "executed": false, "min_domain": -Infinity, "max_domain": Infinity}, {"node_id": 306, "local_id": null, "owner_id": 0, "location": null, "executed": false, "min_domain": -Infinity, "max_domain": Infinity}, {"node_id": 307, "local_id": null, "owner_id": 0, "location": null, "executed": false, "min_domain": -Infinity, "max_domain": Infinity}, {"node_id": 308, "local_id": null, "owner_id": 0, "location": null, "executed": false, "min_domain": -Infinity, "max_domain": Infinity}, {"node_id": 309, "local_id": null, "owner_id": 0, "location": null, "executed": false, "min_domain": -Infinity, "max_domain": Infinity}, {"node_id": 310, "local_id": null, "owner_id": 0, "location": null, "executed": false, "min_domain": -Infinity, "max_domain": Infinity}, {"node_id": 311, "local_id": null, "owner_id": 0, "location": null, "executed": false, "min_domain": -Infinity, "max_domain": Infinity}, {"node_id": 312, "local_id": null, "owner_id": 0, "location": null, "executed": false, "min_domain": -Infinity, "max_domain": Infinity}, {"node_id": 313, "local_id": null, "owner_id": 0, "location": null, "executed": false, "min_domain": -Infinity, "max_domain": Infinity}, {"node_id": 314, "local_id": null, "owner_id": 0, "location": null, "executed": false, "min_domain": -Infinity, "max_domain": Infinity}, {"node_id": 315, "local_id": null, "owner_id": 0, "location": null, "executed": false, "min_domain": -Infinity, "max_domain": Infinity}, {"node_id": 316, "local_id": null, "owner_id": 0, "location": null, "executed": false, "min_domain": -Infinity, "max_domain": Infinity}, {"node_id": 317, "local_id": null, "owner_id": 0, "location": null, "executed": false, "min_domain": -Infinity, "max_domain": Infinity}, {"node_id": 318, "local_id": null, "owner_id": 0, "location": null, "executed": false, "min_domain": -Infinity, "max_domain": Infinity}, {"node_id": 319, "local_id": null, "owner_id": 0, "location": null, "executed": false, "min_domain": -Infinity, "max_domain": Infinity}, {"node_id": 320, "local_id": null, "owner_id": 0, "location": null, "executed": false, "min_domain": -Infinity, "max_domain": Infinity}, {"node_id": 321, "local_id": null, "owner_id": 0, "location": null, "executed": false, "min_domain": -Infinity, "max_domain": Infinity}], "constraints": [{"first_node": 2, "second_node": 3, "distribution": {"name": "U_8.647574952520088_13.995935287083126", "type": "Empirical"}, "min_duration": 8647.574952520088, "max_duration": 13995.935287083126}, {"first_node": 4, "second_node": 5, "distribution": {"name": "U_7.247515389946082_18.671441509905417", "type": "Empirical"}, "min_duration": 7247.515389946082, "max_duration": 18671.441509905417}, {"first_node": 6, "second_node": 7, "distribution": {"name": "U_6.918284242791039_33.48194613245361", "type": "Empirical"}, "min_duration": 6918.284242791039, "max_duration": 33481.94613245361}, {"first_node": 1, "second_node": 2, "min_duration": 0.0, "max_duration": "inf"}, {"first_node": 3, "second_node": 4, "min_duration": 0.0, "max_duration": "inf"}, {"first_node": 5, "second_node": 6, "min_duration": 0.0, "max_duration": "inf"}, {"first_node": 8, "second_node": 9, "distribution": {"name": "N_32.966882072972595_2.6533859633880694", "type": "Empirical"}, "min_duration": "-inf", "max_duration": "inf"}, {"first_node": 10, "second_node": 11, "distribution": {"name": "U_5.5563822371460745_20.932421353135098", "type": "Empirical"}, "min_duration": 5556.382237146075, "max_duration": 20932.421353135098}, {"first_node": 12, "second_node": 13, "distribution": {"name": "U_4.591989494064347_23.937509814355014", "type": "Empirical"}, "min_duration": 4591.989494064346, "max_duration": 23937.509814355013}, {"first_node": 14, "second_node": 15, "distribution": {"name": "U_0.38549679514119806_19.15117779522015", "type": "Empirical"}, "min_duration": 385.49679514119805, "max_duration": 19151.17779522015}, {"first_node": 9, "second_node": 10, "min_duration": 0.0, "max_duration": "inf"}, {"first_node": 11, "second_node": 12, "min_duration": 0.0, "max_duration": "inf"}, {"first_node": 13, "second_node": 14, "min_duration": 0.0, "max_duration": "inf"}, {"first_node": 16, "second_node": 17, "distribution": {"name": "N_37.72901841189261_4.441975101945874", "type": "Empirical"}, "min_duration": "-inf", "max_duration": "inf"}, {"first_node": 18, "second_node": 19, "distribution": {"name": "U_6.891366729274989_24.118177333879444", "type": "Empirical"}, "min_duration": 6891.36672927499, "max_duration": 24118.177333879445}, {"first_node": 20, "second_node": 21, "distribution": {"name": "U_1.0859255984642453_5.091560560979737", "type": "Empirical"}, "min_duration": 1085.9255984642452, "max_duration": 5091.560560979737}, {"first_node": 22, "second_node": 23, "distribution": {"name": "U_7.586909398911928_29.088811060864614", "type": "Empirical"}, "min_duration": 7586.909398911928, "max_duration": 29088.811060864613}, {"first_node": 17, "second_node": 18, "min_duration": 0.0, "max_duration": "inf"}, {"first_node": 19, "second_node": 20, "min_duration": 0.0, "max_duration": "inf"}, {"first_node": 21, "second_node": 22, "min_duration": 0.0, "max_duration": "inf"}, {"first_node": 24, "second_node": 25, "distribution": {"name": "N_73.7151292187804_4.168397823137925", "type": "Empirical"}, "min_duration": "-inf", "max_duration": "inf"}, {"first_node": 26, "second_node": 27, "distribution": {"name": "U_2.9293945998981283_22.867325205633588", "type": "Empirical"}, "min_duration": 2929.3945998981285, "max_duration": 22867.325205633588}, {"first_node": 28, "second_node": 29, "distribution": {"name": "U_5.451171162542397_28.78488239479709", "type": "Empirical"}, "min_duration": 5451.171162542397, "max_duration": 28784.882394797092}, {"first_node": 30, "second_node": 31, "distribution": {"name": "U_6.2683649964457375_28.08271367880345", "type": "Empirical"}, "min_duration": 6268.364996445737, "max_duration": 28082.71367880345}, {"first_node": 25, "second_node": 26, "min_duration": 0.0, "max_duration": "inf"}, {"first_node": 27, "second_node": 28, "min_duration": 0.0, "max_duration": "inf"}, {"first_node": 29, "second_node": 30, "min_duration": 0.0, "max_duration": "inf"}, {"first_node": 32, "second_node": 33, "distribution": {"name": "N_91.7538225081954_3.6461081850139276", "type": "Empirical"}, "min_duration": "-inf", "max_duration": "inf"}, {"first_node": 34, "second_node": 35, "distribution": {"name": "U_5.050785967896867_24.831734184672005", "type": "Empirical"}, "min_duration": 5050.785967896867, "max_duration": 24831.734184672005}, {"first_node": 36, "second_node": 37, "distribution": {"name": "U_5.32579499878609_18.325810584873768", "type": "Empirical"}, "min_duration": 5325.79499878609, "max_duration": 18325.81058487377}, {"first_node": 38, "second_node": 39, "distribution": {"name": "U_4.409298839139341_14.53211408555531", "type": "Empirical"}, "min_duration": 4409.298839139341, "max_duration": 14532.114085555311}, {"first_node": 33, "second_node": 34, "min_duration": 0.0, "max_duration": "inf"}, {"first_node": 35, "second_node": 36, "min_duration": 0.0, "max_duration": "inf"}, {"first_node": 37, "second_node": 38, "min_duration": 0.0, "max_duration": "inf"}, {"first_node": 40, "second_node": 41, "distribution": {"name": "N_13.01414593706005_3.2302679118406443", "type": "Empirical"}, "min_duration": "-inf", "max_duration": "inf"}, {"first_node": 42, "second_node": 43, "distribution": {"name": "U_4.52160646213097_16.741828609526266", "type": "Empirical"}, "min_duration": 4521.606462130971, "max_duration": 16741.828609526267}, {"first_node": 44, "second_node": 45, "distribution": {"name": "U_6.363506860145163_25.080343452666945", "type": "Empirical"}, "min_duration": 6363.506860145163, "max_duration": 25080.343452666944}, {"first_node": 46, "second_node": 47, "distribution": {"name": "U_2.202091127189722_24.322450234036264", "type": "Empirical"}, "min_duration": 2202.091127189722, "max_duration": 24322.450234036263}, {"first_node": 41, "second_node": 42, "min_duration": 0.0, "max_duration": "inf"}, {"first_node": 43, "second_node": 44, "min_duration": 0.0, "max_duration": "inf"}, {"first_node": 45, "second_node": 46, "min_duration": 0.0, "max_duration": "inf"}, {"first_node": 48, "second_node": 49, "distribution": {"name": "N_151.62956770958232_4.225473245981394", "type": "Empirical"}, "min_duration": "-inf", "max_duration": "inf"}, {"first_node": 50, "second_node": 51, "distribution": {"name": "U_4.5108615715160605_21.401614523224833", "type": "Empirical"}, "min_duration": 4510.86157151606, "max_duration": 21401.61452322483}, {"first_node": 52, "second_node": 53, "distribution": {"name": "U_3.0976844084529107_20.83363045183993", "type": "Empirical"}, "min_duration": 3097.6844084529107, "max_duration": 20833.63045183993}, {"first_node": 54, "second_node": 55, "distribution": {"name": "U_7.28928362404627_24.045413552982", "type": "Empirical"}, "min_duration": 7289.28362404627, "max_duration": 24045.413552982}, {"first_node": 49, "second_node": 50, "min_duration": 0.0, "max_duration": "inf"}, {"first_node": 51, "second_node": 52, "min_duration": 0.0, "max_duration": "inf"}, {"first_node": 53, "second_node": 54, "min_duration": 0.0, "max_duration": "inf"}, {"first_node": 6, "second_node": 8, "min_duration": 0.0, "max_duration": "inf"}, {"first_node": 14, "second_node": 16, "min_duration": 0.0, "max_duration": "inf"}, {"first_node": 22, "second_node": 24, "min_duration": 0.0, "max_duration": "inf"}, {"first_node": 30, "second_node": 32, "min_duration": 0.0, "max_duration": "inf"}, {"first_node": 38, "second_node": 40, "min_duration": 0.0, "max_duration": "inf"}, {"first_node": 46, "second_node": 48, "min_duration": 0.0, "max_duration": "inf"}, {"first_node": 56, "second_node": 57, "distribution": {"name": "N_29.24135657952803_2.4887870954979743", "type": "Empirical"}, "min_duration": "-inf", "max_duration": "inf"}, {"first_node": 58, "second_node": 59, "distribution": {"name": "U_5.646590684498885_9.359221255255965", "type": "Empirical"}, "min_duration": 5646.590684498885, "max_duration": 9359.221255255965}, {"first_node": 54, "second_node": 56, "min_duration": 0.0, "max_duration": "inf"}, {"first_node": 57, "second_node": 58, "min_duration": 0.0, "max_duration": "inf"}, {"first_node": 60, "second_node": 0, "min_duration": 0.0, "max_duration": "inf"}, {"first_node": 59, "second_node": 61, "min_duration": 0.0, "max_duration": "inf"}, {"first_node": 62, "second_node": 63, "distribution": {"name": "N_137.1845145547565_3.5811114715613437", "type": "Empirical"}, "min_duration": "-inf", "max_duration": "inf"}, {"first_node": 64, "second_node": 65, "distribution": {"name": "U_6.966799476811262_25.765926812213117", "type": "Empirical"}, "min_duration": 6966.799476811262, "max_duration": 25765.926812213118}, {"first_node": 66, "second_node": 67, "distribution": {"name": "U_5.3624789060677704_22.990901734596026", "type": "Empirical"}, "min_duration": 5362.47890606777, "max_duration": 22990.901734596027}, {"first_node": 68, "second_node": 69, "distribution": {"name": "U_4.819349486458377_22.904406167874903", "type": "Empirical"}, "min_duration": 4819.349486458376, "max_duration": 22904.406167874902}, {"first_node": 63, "second_node": 64, "min_duration": 0.0, "max_duration": "inf"}, {"first_node": 65, "second_node": 66, "min_duration": 0.0, "max_duration": "inf"}, {"first_node": 67, "second_node": 68, "min_duration": 0.0, "max_duration": "inf"}, {"first_node": 70, "second_node": 71, "distribution": {"name": "N_4.0236026415716_3.968812120218107", "type": "Empirical"}, "min_duration": "-inf", "max_duration": "inf"}, {"first_node": 72, "second_node": 73, "distribution": {"name": "U_3.8210272491604576_26.89586358213162", "type": "Empirical"}, "min_duration": 3821.0272491604574, "max_duration": 26895.86358213162}, {"first_node": 74, "second_node": 75, "distribution": {"name": "U_4.540774882347115_16.02812596169486", "type": "Empirical"}, "min_duration": 4540.774882347116, "max_duration": 16028.125961694861}, {"first_node": 76, "second_node": 77, "distribution": {"name": "U_4.592040126949931_17.776751435335058", "type": "Empirical"}, "min_duration": 4592.040126949932, "max_duration": 17776.751435335056}, {"first_node": 71, "second_node": 72, "min_duration": 0.0, "max_duration": "inf"}, {"first_node": 73, "second_node": 74, "min_duration": 0.0, "max_duration": "inf"}, {"first_node": 75, "second_node": 76, "min_duration": 0.0, "max_duration": "inf"}, {"first_node": 68, "second_node": 70, "min_duration": 0.0, "max_duration": "inf"}, {"first_node": 78, "second_node": 79, "distribution": {"name": "N_95.35737730731307_3.032997615577016", "type": "Empirical"}, "min_duration": "-inf", "max_duration": "inf"}, {"first_node": 80, "second_node": 81, "distribution": {"name": "U_1.877500791488794_4.461806564314264", "type": "Empirical"}, "min_duration": 1877.500791488794, "max_duration": 4461.806564314264}, {"first_node": 76, "second_node": 78, "min_duration": 0.0, "max_duration": "inf"}, {"first_node": 79, "second_node": 80, "min_duration": 0.0, "max_duration": "inf"}, {"first_node": 60, "second_node": 62, "min_duration": 0.0, "max_duration": "inf"}, {"first_node": 81, "second_node": 61, "min_duration": 0.0, "max_duration": "inf"}, {"first_node": 82, "second_node": 83, "distribution": {"name": "N_100.14116219251495_2.8375424116340264", "type": "Empirical"}, "min_duration": "-inf", "max_duration": "inf"}, {"first_node": 84, "second_node": 85, "distribution": {"name": "U_6.916387699527001_23.742609177467074", "type": "Empirical"}, "min_duration": 6916.387699527001, "max_duration": 23742.609177467075}, {"first_node": 86, "second_node": 87, "distribution": {"name": "U_2.3342555078595932_17.275892287149336", "type": "Empirical"}, "min_duration": 2334.2555078595933, "max_duration": 17275.892287149338}, {"first_node": 88, "second_node": 89, "distribution": {"name": "U_1.9919213275674266_14.429117823602356", "type": "Empirical"}, "min_duration": 1991.9213275674265, "max_duration": 14429.117823602355}, {"first_node": 83, "second_node": 84, "min_duration": 0.0, "max_duration": "inf"}, {"first_node": 85, "second_node": 86, "min_duration": 0.0, "max_duration": "inf"}, {"first_node": 87, "second_node": 88, "min_duration": 0.0, "max_duration": "inf"}, {"first_node": 90, "second_node": 91, "distribution": {"name": "N_47.02344626500511_4.072651452814173", "type": "Empirical"}, "min_duration": "-inf", "max_duration": "inf"}, {"first_node": 92, "second_node": 93, "distribution": {"name": "U_1.6885438853721033_23.0907529787322", "type": "Empirical"}, "min_duration": 1688.5438853721032, "max_duration": 23090.752978732202}, {"first_node": 94, "second_node": 95, "distribution": {"name": "U_3.5850295421288574_22.55931675464729", "type": "Empirical"}, "min_duration": 3585.0295421288574, "max_duration": 22559.31675464729}, {"first_node": 96, "second_node": 97, "distribution": {"name": "U_3.3458293241869894_17.335041198248188", "type": "Empirical"}, "min_duration": 3345.829324186989, "max_duration": 17335.04119824819}, {"first_node": 91, "second_node": 92, "min_duration": 0.0, "max_duration": "inf"}, {"first_node": 93, "second_node": 94, "min_duration": 0.0, "max_duration": "inf"}, {"first_node": 95, "second_node": 96, "min_duration": 0.0, "max_duration": "inf"}, {"first_node": 88, "second_node": 90, "min_duration": 0.0, "max_duration": "inf"}, {"first_node": 98, "second_node": 99, "distribution": {"name": "N_111.11010667231848_4.83288216856784", "type": "Empirical"}, "min_duration": "-inf", "max_duration": "inf"}, {"first_node": 100, "second_node": 101, "distribution": {"name": "U_3.9836811401217265_6.808489229062383", "type": "Empirical"}, "min_duration": 3983.6811401217265, "max_duration": 6808.489229062383}, {"first_node": 96, "second_node": 98, "min_duration": 0.0, "max_duration": "inf"}, {"first_node": 99, "second_node": 100, "min_duration": 0.0, "max_duration": "inf"}, {"first_node": 60, "second_node": 82, "min_duration": 0.0, "max_duration": "inf"}, {"first_node": 101, "second_node": 61, "min_duration": 0.0, "max_duration": "inf"}, {"first_node": 102, "second_node": 103, "distribution": {"name": "N_79.39822088013798_4.622393246339396", "type": "Empirical"}, "min_duration": "-inf", "max_duration": "inf"}, {"first_node": 104, "second_node": 105, "distribution": {"name": "U_0.9418777239399976_20.0353887089148", "type": "Empirical"}, "min_duration": 941.8777239399976, "max_duration": 20035.3887089148}, {"first_node": 106, "second_node": 107, "distribution": {"name": "U_6.2582762419980416_18.869336067727417", "type": "Empirical"}, "min_duration": 6258.276241998042, "max_duration": 18869.336067727418}, {"first_node": 108, "second_node": 109, "distribution": {"name": "U_10.310774443897474_22.26210979808235", "type": "Empirical"}, "min_duration": 10310.774443897473, "max_duration": 22262.10979808235}, {"first_node": 103, "second_node": 104, "min_duration": 0.0, "max_duration": "inf"}, {"first_node": 105, "second_node": 106, "min_duration": 0.0, "max_duration": "inf"}, {"first_node": 107, "second_node": 108, "min_duration": 0.0, "max_duration": "inf"}, {"first_node": 110, "second_node": 111, "distribution": {"name": "N_95.64683247473376_3.842413887368925", "type": "Empirical"}, "min_duration": "-inf", "max_duration": "inf"}, {"first_node": 112, "second_node": 113, "distribution": {"name": "U_4.713414643522833_6.985380163634137", "type": "Empirical"}, "min_duration": 4713.414643522832, "max_duration": 6985.380163634137}, {"first_node": 108, "second_node": 110, "min_duration": 0.0, "max_duration": "inf"}, {"first_node": 111, "second_node": 112, "min_duration": 0.0, "max_duration": "inf"}, {"first_node": 60, "second_node": 102, "min_duration": 0.0, "max_duration": "inf"}, {"first_node": 113, "second_node": 61, "min_duration": 0.0, "max_duration": "inf"}, {"first_node": 114, "second_node": 115, "distribution": {"name": "N_77.25184499581485_3.447138353537865", "type": "Empirical"}, "min_duration": "-inf", "max_duration": "inf"}, {"first_node": 116, "second_node": 117, "distribution": {"name": "U_4.887218295704224_10.304448960521018", "type": "Empirical"}, "min_duration": 4887.218295704223, "max_duration": 10304.448960521018}, {"first_node": 118, "second_node": 119, "distribution": {"name": "U_4.018998390119883_16.269795883548287", "type": "Empirical"}, "min_duration": 4018.998390119883, "max_duration": 16269.795883548288}, {"first_node": 120, "second_node": 121, "distribution": {"name": "U_4.273330075556363_22.459472614645353", "type": "Empirical"}, "min_duration": 4273.330075556362, "max_duration": 22459.472614645354}, {"first_node": 115, "second_node": 116, "min_duration": 0.0, "max_duration": "inf"}, {"first_node": 117, "second_node": 118, "min_duration": 0.0, "max_duration": "inf"}, {"first_node": 119, "second_node": 120, "min_duration": 0.0, "max_duration": "inf"}, {"first_node": 122, "second_node": 123, "distribution": {"name": "N_123.80858599547038_4.134275327834501", "type": "Empirical"}, "min_duration": "-inf", "max_duration": "inf"}, {"first_node": 124, "second_node": 125, "distribution": {"name": "U_3.684246068395021_18.791159038441855", "type": "Empirical"}, "min_duration": 3684.246068395021, "max_duration": 18791.159038441856}, {"first_node": 126, "second_node": 127, "distribution": {"name": "U_2.133950606746218_18.72364554539064", "type": "Empirical"}, "min_duration": 2133.950606746218, "max_duration": 18723.64554539064}, {"first_node": 128, "second_node": 129, "distribution": {"name": "U_8.663107013569759_24.864075089486413", "type": "Empirical"}, "min_duration": 8663.10701356976, "max_duration": 24864.075089486414}, {"first_node": 123, "second_node": 124, "min_duration": 0.0, "max_duration": "inf"}, {"first_node": 125, "second_node": 126, "min_duration": 0.0, "max_duration": "inf"}, {"first_node": 127, "second_node": 128, "min_duration": 0.0, "max_duration": "inf"}, {"first_node": 130, "second_node": 131, "distribution": {"name": "N_64.87006850212303_3.3925048688192847", "type": "Empirical"}, "min_duration": "-inf", "max_duration": "inf"}, {"first_node": 132, "second_node": 133, "distribution": {"name": "U_2.7107608312578964_12.48276582377897", "type": "Empirical"}, "min_duration": 2710.7608312578964, "max_duration": 12482.76582377897}, {"first_node": 134, "second_node": 135, "distribution": {"name": "U_5.688538095900281_16.888582846001125", "type": "Empirical"}, "min_duration": 5688.5380959002805, "max_duration": 16888.582846001125}, {"first_node": 136, "second_node": 137, "distribution": {"name": "U_8.794995425083336_15.679780792298693", "type": "Empirical"}, "min_duration": 8794.995425083336, "max_duration": 15679.780792298694}, {"first_node": 131, "second_node": 132, "min_duration": 0.0, "max_duration": "inf"}, {"first_node": 133, "second_node": 134, "min_duration": 0.0, "max_duration": "inf"}, {"first_node": 135, "second_node": 136, "min_duration": 0.0, "max_duration": "inf"}, {"first_node": 138, "second_node": 139, "distribution": {"name": "N_75.01334468268875_2.184964364405087", "type": "Empirical"}, "min_duration": "-inf", "max_duration": "inf"}, {"first_node": 140, "second_node": 141, "distribution": {"name": "U_2.7986768669653546_16.575735253673514", "type": "Empirical"}, "min_duration": 2798.6768669653547, "max_duration": 16575.735253673512}, {"first_node": 142, "second_node": 143, "distribution": {"name": "U_10.347310041941896_25.556621349234582", "type": "Empirical"}, "min_duration": 10347.310041941895, "max_duration": 25556.62134923458}, {"first_node": 144, "second_node": 145, "distribution": {"name": "U_3.6378320874079235_15.439553607370472", "type": "Empirical"}, "min_duration": 3637.8320874079236, "max_duration": 15439.553607370472}, {"first_node": 139, "second_node": 140, "min_duration": 0.0, "max_duration": "inf"}, {"first_node": 141, "second_node": 142, "min_duration": 0.0, "max_duration": "inf"}, {"first_node": 143, "second_node": 144, "min_duration": 0.0, "max_duration": "inf"}, {"first_node": 146, "second_node": 147, "distribution": {"name": "N_5.200943393374402_3.6664772394220937", "type": "Empirical"}, "min_duration": "-inf", "max_duration": "inf"}, {"first_node": 148, "second_node": 149, "distribution": {"name": "U_6.683689896983946_24.222961739491453", "type": "Empirical"}, "min_duration": 6683.689896983946, "max_duration": 24222.961739491453}, {"first_node": 150, "second_node": 151, "distribution": {"name": "U_3.2427855051008962_18.387509151004924", "type": "Empirical"}, "min_duration": 3242.7855051008964, "max_duration": 18387.509151004924}, {"first_node": 152, "second_node": 153, "distribution": {"name": "U_4.4553534441820535_21.899297083645266", "type": "Empirical"}, "min_duration": 4455.353444182054, "max_duration": 21899.297083645266}, {"first_node": 147, "second_node": 148, "min_duration": 0.0, "max_duration": "inf"}, {"first_node": 149, "second_node": 150, "min_duration": 0.0, "max_duration": "inf"}, {"first_node": 151, "second_node": 152, "min_duration": 0.0, "max_duration": "inf"}, {"first_node": 154, "second_node": 155, "distribution": {"name": "N_108.45791188489778_4.572997693550746", "type": "Empirical"}, "min_duration": "-inf", "max_duration": "inf"}, {"first_node": 156, "second_node": 157, "distribution": {"name": "U_6.707029512655296_22.694242294122308", "type": "Empirical"}, "min_duration": 6707.0295126552965, "max_duration": 22694.24229412231}, {"first_node": 158, "second_node": 159, "distribution": {"name": "U_4.60129405110738_25.223837842050386", "type": "Empirical"}, "min_duration": 4601.29405110738, "max_duration": 25223.837842050387}, {"first_node": 160, "second_node": 161, "distribution": {"name": "U_5.145052670612109_18.9366903064503", "type": "Empirical"}, "min_duration": 5145.052670612109, "max_duration": 18936.6903064503}, {"first_node": 155, "second_node": 156, "min_duration": 0.0, "max_duration": "inf"}, {"first_node": 157, "second_node": 158, "min_duration": 0.0, "max_duration": "inf"}, {"first_node": 159, "second_node": 160, "min_duration": 0.0, "max_duration": "inf"}, {"first_node": 162, "second_node": 163, "distribution": {"name": "N_142.52504724283864_3.5083686210889753", "type": "Empirical"}, "min_duration": "-inf", "max_duration": "inf"}, {"first_node": 164, "second_node": 165, "distribution": {"name": "U_5.194180320890322_17.956831229739187", "type": "Empirical"}, "min_duration": 5194.180320890322, "max_duration": 17956.831229739186}, {"first_node": 166, "second_node": 167, "distribution": {"name": "U_5.944663139841676_18.148329987069985", "type": "Empirical"}, "min_duration": 5944.663139841677, "max_duration": 18148.329987069985}, {"first_node": 168, "second_node": 169, "distribution": {"name": "U_2.4451662384325643_15.391930761818006", "type": "Empirical"}, "min_duration": 2445.166238432564, "max_duration": 15391.930761818006}, {"first_node": 163, "second_node": 164, "min_duration": 0.0, "max_duration": "inf"}, {"first_node": 165, "second_node": 166, "min_duration": 0.0, "max_duration": "inf"}, {"first_node": 167, "second_node": 168, "min_duration": 0.0, "max_duration": "inf"}, {"first_node": 120, "second_node": 122, "min_duration": 0.0, "max_duration": "inf"}, {"first_node": 128, "second_node": 130, "min_duration": 0.0, "max_duration": "inf"}, {"first_node": 136, "second_node": 138, "min_duration": 0.0, "max_duration": "inf"}, {"first_node": 144, "second_node": 146, "min_duration": 0.0, "max_duration": "inf"}, {"first_node": 152, "second_node": 154, "min_duration": 0.0, "max_duration": "inf"}, {"first_node": 160, "second_node": 162, "min_duration": 0.0, "max_duration": "inf"}, {"first_node": 170, "second_node": 171, "distribution": {"name": "N_90.97609376559072_5.097003803626758", "type": "Empirical"}, "min_duration": "-inf", "max_duration": "inf"}, {"first_node": 172, "second_node": 173, "distribution": {"name": "U_7.716611228495815_10.803184272349228", "type": "Empirical"}, "min_duration": 7716.611228495814, "max_duration": 10803.184272349228}, {"first_node": 168, "second_node": 170, "min_duration": 0.0, "max_duration": "inf"}, {"first_node": 171, "second_node": 172, "min_duration": 0.0, "max_duration": "inf"}, {"first_node": 60, "second_node": 114, "min_duration": 0.0, "max_duration": "inf"}, {"first_node": 173, "second_node": 61, "min_duration": 0.0, "max_duration": "inf"}, {"first_node": 174, "second_node": 175, "distribution": {"name": "N_2.6678576171569546_4.363533074230484", "type": "Empirical"}, "min_duration": "-inf", "max_duration": "inf"}, {"first_node": 176, "second_node": 177, "distribution": {"name": "U_3.168598069924558_13.655345037236183", "type": "Empirical"}, "min_duration": 3168.598069924558, "max_duration": 13655.345037236182}, {"first_node": 178, "second_node": 179, "distribution": {"name": "U_1.5207731365145678_18.32432918089957", "type": "Empirical"}, "min_duration": 1520.7731365145678, "max_duration": 18324.32918089957}, {"first_node": 180, "second_node": 181, "distribution": {"name": "U_3.9227589890953984_15.20252688350115", "type": "Empirical"}, "min_duration": 3922.7589890953986, "max_duration": 15202.52688350115}, {"first_node": 175, "second_node": 176, "min_duration": 0.0, "max_duration": "inf"}, {"first_node": 177, "second_node": 178, "min_duration": 0.0, "max_duration": "inf"}, {"first_node": 179, "second_node": 180, "min_duration": 0.0, "max_duration": "inf"}, {"first_node": 182, "second_node": 183, "distribution": {"name": "N_139.70557072774818_1.2557345485043194", "type": "Empirical"}, "min_duration": "-inf", "max_duration": "inf"}, {"first_node": 184, "second_node": 185, "distribution": {"name": "U_4.759819405037887_13.989355623620558", "type": "Empirical"}, "min_duration": 4759.819405037887, "max_duration": 13989.355623620557}, {"first_node": 186, "second_node": 187, "distribution": {"name": "U_5.866643017431135_7.556196166269912", "type": "Empirical"}, "min_duration": 5866.6430174311345, "max_duration": 7556.196166269912}, {"first_node": 188, "second_node": 189, "distribution": {"name": "U_3.4878500955917566_18.960628351728104", "type": "Empirical"}, "min_duration": 3487.8500955917566, "max_duration": 18960.628351728104}, {"first_node": 183, "second_node": 184, "min_duration": 0.0, "max_duration": "inf"}, {"first_node": 185, "second_node": 186, "min_duration": 0.0, "max_duration": "inf"}, {"first_node": 187, "second_node": 188, "min_duration": 0.0, "max_duration": "inf"}, {"first_node": 190, "second_node": 191, "distribution": {"name": "N_121.73030846700576_4.054746522549798", "type": "Empirical"}, "min_duration": "-inf", "max_duration": "inf"}, {"first_node": 192, "second_node": 193, "distribution": {"name": "U_4.66279272927066_19.479668316257293", "type": "Empirical"}, "min_duration": 4662.79272927066, "max_duration": 19479.66831625729}, {"first_node": 194, "second_node": 195, "distribution": {"name": "U_7.459018625403468_11.246087369305224", "type": "Empirical"}, "min_duration": 7459.018625403468, "max_duration": 11246.087369305224}, {"first_node": 196, "second_node": 197, "distribution": {"name": "U_2.9869676230936895_10.753279001652736", "type": "Empirical"}, "min_duration": 2986.9676230936893, "max_duration": 10753.279001652736}, {"first_node": 191, "second_node": 192, "min_duration": 0.0, "max_duration": "inf"}, {"first_node": 193, "second_node": 194, "min_duration": 0.0, "max_duration": "inf"}, {"first_node": 195, "second_node": 196, "min_duration": 0.0, "max_duration": "inf"}, {"first_node": 198, "second_node": 199, "distribution": {"name": "N_81.19914594814801_4.661467789718536", "type": "Empirical"}, "min_duration": "-inf", "max_duration": "inf"}, {"first_node": 200, "second_node": 201, "distribution": {"name": "U_6.839662138246421_25.088564466271666", "type": "Empirical"}, "min_duration": 6839.662138246421, "max_duration": 25088.564466271666}, {"first_node": 202, "second_node": 203, "distribution": {"name": "U_5.503612805671572_27.344410942963655", "type": "Empirical"}, "min_duration": 5503.612805671572, "max_duration": 27344.410942963656}, {"first_node": 204, "second_node": 205, "distribution": {"name": "U_1.7065093945654768_21.887397594684494", "type": "Empirical"}, "min_duration": 1706.509394565477, "max_duration": 21887.397594684495}, {"first_node": 199, "second_node": 200, "min_duration": 0.0, "max_duration": "inf"}, {"first_node": 201, "second_node": 202, "min_duration": 0.0, "max_duration": "inf"}, {"first_node": 203, "second_node": 204, "min_duration": 0.0, "max_duration": "inf"}, {"first_node": 206, "second_node": 207, "distribution": {"name": "N_105.64386709423682_4.727873357848928", "type": "Empirical"}, "min_duration": "-inf", "max_duration": "inf"}, {"first_node": 208, "second_node": 209, "distribution": {"name": "U_3.5479312992844347_20.749068150701376", "type": "Empirical"}, "min_duration": 3547.9312992844348, "max_duration": 20749.068150701376}, {"first_node": 210, "second_node": 211, "distribution": {"name": "U_4.064935120094551_12.225450360075373", "type": "Empirical"}, "min_duration": 4064.935120094551, "max_duration": 12225.450360075372}, {"first_node": 212, "second_node": 213, "distribution": {"name": "U_6.871687564232409_14.241056610204367", "type": "Empirical"}, "min_duration": 6871.6875642324085, "max_duration": 14241.056610204367}, {"first_node": 207, "second_node": 208, "min_duration": 0.0, "max_duration": "inf"}, {"first_node": 209, "second_node": 210, "min_duration": 0.0, "max_duration": "inf"}, {"first_node": 211, "second_node": 212, "min_duration": 0.0, "max_duration": "inf"}, {"first_node": 214, "second_node": 215, "distribution": {"name": "N_88.63343083818086_3.836219254449968", "type": "Empirical"}, "min_duration": "-inf", "max_duration": "inf"}, {"first_node": 216, "second_node": 217, "distribution": {"name": "U_4.242457043454215_21.549947446638644", "type": "Empirical"}, "min_duration": 4242.457043454216, "max_duration": 21549.947446638645}, {"first_node": 218, "second_node": 219, "distribution": {"name": "U_5.197185482372234_24.592149262885698", "type": "Empirical"}, "min_duration": 5197.185482372234, "max_duration": 24592.149262885698}, {"first_node": 220, "second_node": 221, "distribution": {"name": "U_4.828424040810104_20.185762204779767", "type": "Empirical"}, "min_duration": 4828.424040810104, "max_duration": 20185.762204779767}, {"first_node": 215, "second_node": 216, "min_duration": 0.0, "max_duration": "inf"}, {"first_node": 217, "second_node": 218, "min_duration": 0.0, "max_duration": "inf"}, {"first_node": 219, "second_node": 220, "min_duration": 0.0, "max_duration": "inf"}, {"first_node": 222, "second_node": 223, "distribution": {"name": "N_111.68482053816462_2.878494567343886", "type": "Empirical"}, "min_duration": "-inf", "max_duration": "inf"}, {"first_node": 224, "second_node": 225, "distribution": {"name": "U_5.932528438587456_26.330922906885725", "type": "Empirical"}, "min_duration": 5932.528438587456, "max_duration": 26330.922906885724}, {"first_node": 226, "second_node": 227, "distribution": {"name": "U_1.0668462051902248_18.0766056708837", "type": "Empirical"}, "min_duration": 1066.8462051902247, "max_duration": 18076.605670883702}, {"first_node": 228, "second_node": 229, "distribution": {"name": "U_2.6776752182598753_13.03784820649842", "type": "Empirical"}, "min_duration": 2677.6752182598752, "max_duration": 13037.84820649842}, {"first_node": 223, "second_node": 224, "min_duration": 0.0, "max_duration": "inf"}, {"first_node": 225, "second_node": 226, "min_duration": 0.0, "max_duration": "inf"}, {"first_node": 227, "second_node": 228, "min_duration": 0.0, "max_duration": "inf"}, {"first_node": 230, "second_node": 231, "distribution": {"name": "N_107.2580946670219_3.663142969843488", "type": "Empirical"}, "min_duration": "-inf", "max_duration": "inf"}, {"first_node": 232, "second_node": 233, "distribution": {"name": "U_3.49711346088292_16.3780794928224", "type": "Empirical"}, "min_duration": 3497.1134608829198, "max_duration": 16378.0794928224}, {"first_node": 234, "second_node": 235, "distribution": {"name": "U_6.492365209484613_19.391059044057766", "type": "Empirical"}, "min_duration": 6492.365209484613, "max_duration": 19391.059044057765}, {"first_node": 236, "second_node": 237, "distribution": {"name": "U_8.004517192125997_17.269851342110087", "type": "Empirical"}, "min_duration": 8004.517192125997, "max_duration": 17269.851342110087}, {"first_node": 231, "second_node": 232, "min_duration": 0.0, "max_duration": "inf"}, {"first_node": 233, "second_node": 234, "min_duration": 0.0, "max_duration": "inf"}, {"first_node": 235, "second_node": 236, "min_duration": 0.0, "max_duration": "inf"}, {"first_node": 180, "second_node": 182, "min_duration": 0.0, "max_duration": "inf"}, {"first_node": 188, "second_node": 190, "min_duration": 0.0, "max_duration": "inf"}, {"first_node": 196, "second_node": 198, "min_duration": 0.0, "max_duration": "inf"}, {"first_node": 204, "second_node": 206, "min_duration": 0.0, "max_duration": "inf"}, {"first_node": 212, "second_node": 214, "min_duration": 0.0, "max_duration": "inf"}, {"first_node": 220, "second_node": 222, "min_duration": 0.0, "max_duration": "inf"}, {"first_node": 228, "second_node": 230, "min_duration": 0.0, "max_duration": "inf"}, {"first_node": 238, "second_node": 239, "distribution": {"name": "N_105.51569384631323_4.56889392306308", "type": "Empirical"}, "min_duration": "-inf", "max_duration": "inf"}, {"first_node": 240, "second_node": 241, "distribution": {"name": "U_4.297319184571684_7.014550703023516", "type": "Empirical"}, "min_duration": 4297.319184571684, "max_duration": 7014.550703023516}, {"first_node": 236, "second_node": 238, "min_duration": 0.0, "max_duration": "inf"}, {"first_node": 239, "second_node": 240, "min_duration": 0.0, "max_duration": "inf"}, {"first_node": 60, "second_node": 174, "min_duration": 0.0, "max_duration": "inf"}, {"first_node": 241, "second_node": 61, "min_duration": 0.0, "max_duration": "inf"}, {"first_node": 242, "second_node": 243, "distribution": {"name": "N_139.3412756325993_4.302915299654724", "type": "Empirical"}, "min_duration": "-inf", "max_duration": "inf"}, {"first_node": 244, "second_node": 245, "distribution": {"name": "U_5.493058167607127_19.821981719821913", "type": "Empirical"}, "min_duration": 5493.058167607127, "max_duration": 19821.981719821913}, {"first_node": 246, "second_node": 247, "distribution": {"name": "U_3.3786839056653335_17.839075706488437", "type": "Empirical"}, "min_duration": 3378.6839056653334, "max_duration": 17839.07570648844}, {"first_node": 248, "second_node": 249, "distribution": {"name": "U_3.8522356168638536_20.930674154252703", "type": "Empirical"}, "min_duration": 3852.2356168638535, "max_duration": 20930.6741542527}, {"first_node": 243, "second_node": 244, "min_duration": 0.0, "max_duration": "inf"}, {"first_node": 245, "second_node": 246, "min_duration": 0.0, "max_duration": "inf"}, {"first_node": 247, "second_node": 248, "min_duration": 0.0, "max_duration": "inf"}, {"first_node": 250, "second_node": 251, "distribution": {"name": "N_89.76216340989569_3.5636591985421626", "type": "Empirical"}, "min_duration": "-inf", "max_duration": "inf"}, {"first_node": 252, "second_node": 253, "distribution": {"name": "U_3.123980717519106_14.078411117914413", "type": "Empirical"}, "min_duration": 3123.980717519106, "max_duration": 14078.411117914413}, {"first_node": 254, "second_node": 255, "distribution": {"name": "U_2.482371254509621_14.147451238584862", "type": "Empirical"}, "min_duration": 2482.371254509621, "max_duration": 14147.451238584863}, {"first_node": 256, "second_node": 257, "distribution": {"name": "U_7.104987240537671_32.183752930929145", "type": "Empirical"}, "min_duration": 7104.987240537671, "max_duration": 32183.752930929146}, {"first_node": 251, "second_node": 252, "min_duration": 0.0, "max_duration": "inf"}, {"first_node": 253, "second_node": 254, "min_duration": 0.0, "max_duration": "inf"}, {"first_node": 255, "second_node": 256, "min_duration": 0.0, "max_duration": "inf"}, {"first_node": 258, "second_node": 259, "distribution": {"name": "N_109.1892819781534_3.9220933854082265", "type": "Empirical"}, "min_duration": "-inf", "max_duration": "inf"}, {"first_node": 260, "second_node": 261, "distribution": {"name": "U_2.4898380147899473_19.760621846718315", "type": "Empirical"}, "min_duration": 2489.8380147899475, "max_duration": 19760.621846718317}, {"first_node": 262, "second_node": 263, "distribution": {"name": "U_2.0231472605497225_18.55692830220617", "type": "Empirical"}, "min_duration": 2023.1472605497224, "max_duration": 18556.92830220617}, {"first_node": 264, "second_node": 265, "distribution": {"name": "U_7.300928885642625_21.8074848434693", "type": "Empirical"}, "min_duration": 7300.928885642625, "max_duration": 21807.4848434693}, {"first_node": 259, "second_node": 260, "min_duration": 0.0, "max_duration": "inf"}, {"first_node": 261, "second_node": 262, "min_duration": 0.0, "max_duration": "inf"}, {"first_node": 263, "second_node": 264, "min_duration": 0.0, "max_duration": "inf"}, {"first_node": 248, "second_node": 250, "min_duration": 0.0, "max_duration": "inf"}, {"first_node": 256, "second_node": 258, "min_duration": 0.0, "max_duration": "inf"}, {"first_node": 266, "second_node": 267, "distribution": {"name": "N_158.0470148272727_3.8444701804224235", "type": "Empirical"}, "min_duration": "-inf", "max_duration": "inf"}, {"first_node": 268, "second_node": 269, "distribution": {"name": "U_4.845182433138993_7.348044915473391", "type": "Empirical"}, "min_duration": 4845.1824331389935, "max_duration": 7348.0449154733915}, {"first_node": 264, "second_node": 266, "min_duration": 0.0, "max_duration": "inf"}, {"first_node": 267, "second_node": 268, "min_duration": 0.0, "max_duration": "inf"}, {"first_node": 60, "second_node": 242, "min_duration": 0.0, "max_duration": "inf"}, {"first_node": 269, "second_node": 61, "min_duration": 0.0, "max_duration": "inf"}, {"first_node": 270, "second_node": 271, "distribution": {"name": "N_34.1221016784312_4.112175878078148", "type": "Empirical"}, "min_duration": "-inf", "max_duration": "inf"}, {"first_node": 272, "second_node": 273, "distribution": {"name": "U_7.396527351965638_24.72110296968711", "type": "Empirical"}, "min_duration": 7396.5273519656375, "max_duration": 24721.10296968711}, {"first_node": 274, "second_node": 275, "distribution": {"name": "U_9.709327923515616_26.055009994742935", "type": "Empirical"}, "min_duration": 9709.327923515615, "max_duration": 26055.009994742933}, {"first_node": 276, "second_node": 277, "distribution": {"name": "U_3.070857774921869_22.228102108466466", "type": "Empirical"}, "min_duration": 3070.857774921869, "max_duration": 22228.102108466464}, {"first_node": 271, "second_node": 272, "min_duration": 0.0, "max_duration": "inf"}, {"first_node": 273, "second_node": 274, "min_duration": 0.0, "max_duration": "inf"}, {"first_node": 275, "second_node": 276, "min_duration": 0.0, "max_duration": "inf"}, {"first_node": 278, "second_node": 279, "distribution": {"name": "N_138.08616406731488_3.6544847397795333", "type": "Empirical"}, "min_duration": "-inf", "max_duration": "inf"}, {"first_node": 280, "second_node": 281, "distribution": {"name": "U_5.690715484442244_20.955455553669616", "type": "Empirical"}, "min_duration": 5690.715484442244, "max_duration": 20955.455553669617}, {"first_node": 282, "second_node": 283, "distribution": {"name": "U_7.623392638168964_26.16604940543148", "type": "Empirical"}, "min_duration": 7623.3926381689635, "max_duration": 26166.04940543148}, {"first_node": 284, "second_node": 285, "distribution": {"name": "U_5.279481478853861_14.24321215127847", "type": "Empirical"}, "min_duration": 5279.4814788538615, "max_duration": 14243.21215127847}, {"first_node": 279, "second_node": 280, "min_duration": 0.0, "max_duration": "inf"}, {"first_node": 281, "second_node": 282, "min_duration": 0.0, "max_duration": "inf"}, {"first_node": 283, "second_node": 284, "min_duration": 0.0, "max_duration": "inf"}, {"first_node": 286, "second_node": 287, "distribution": {"name": "N_82.30183638595432_4.8207438987092335", "type": "Empirical"}, "min_duration": "-inf", "max_duration": "inf"}, {"first_node": 288, "second_node": 289, "distribution": {"name": "U_4.260154718070477_18.998684093585055", "type": "Empirical"}, "min_duration": 4260.1547180704765, "max_duration": 18998.684093585056}, {"first_node": 290, "second_node": 291, "distribution": {"name": "U_2.952034653049379_18.140616525712232", "type": "Empirical"}, "min_duration": 2952.034653049379, "max_duration": 18140.616525712234}, {"first_node": 292, "second_node": 293, "distribution": {"name": "U_6.33057365219281_33.73302811651123", "type": "Empirical"}, "min_duration": 6330.57365219281, "max_duration": 33733.028116511225}, {"first_node": 287, "second_node": 288, "min_duration": 0.0, "max_duration": "inf"}, {"first_node": 289, "second_node": 290, "min_duration": 0.0, "max_duration": "inf"}, {"first_node": 291, "second_node": 292, "min_duration": 0.0, "max_duration": "inf"}, {"first_node": 294, "second_node": 295, "distribution": {"name": "N_22.730347623555588_4.945840913185793", "type": "Empirical"}, "min_duration": "-inf", "max_duration": "inf"}, {"first_node": 296, "second_node": 297, "distribution": {"name": "U_8.24051992477376_15.122437937242386", "type": "Empirical"}, "min_duration": 8240.51992477376, "max_duration": 15122.437937242386}, {"first_node": 298, "second_node": 299, "distribution": {"name": "U_1.2743172933712859_14.347068058511686", "type": "Empirical"}, "min_duration": 1274.3172933712858, "max_duration": 14347.068058511686}, {"first_node": 300, "second_node": 301, "distribution": {"name": "U_3.9756208379950295_24.00025616426986", "type": "Empirical"}, "min_duration": 3975.6208379950294, "max_duration": 24000.25616426986}, {"first_node": 295, "second_node": 296, "min_duration": 0.0, "max_duration": "inf"}, {"first_node": 297, "second_node": 298, "min_duration": 0.0, "max_duration": "inf"}, {"first_node": 299, "second_node": 300, "min_duration": 0.0, "max_duration": "inf"}, {"first_node": 302, "second_node": 303, "distribution": {"name": "N_29.010551334559203_4.36275253240695", "type": "Empirical"}, "min_duration": "-inf", "max_duration": "inf"}, {"first_node": 304, "second_node": 305, "distribution": {"name": "U_5.59738580445314_23.432655804582936", "type": "Empirical"}, "min_duration": 5597.38580445314, "max_duration": 23432.655804582937}, {"first_node": 306, "second_node": 307, "distribution": {"name": "U_9.174955494721164_33.10652346417055", "type": "Empirical"}, "min_duration": 9174.955494721164, "max_duration": 33106.52346417055}, {"first_node": 308, "second_node": 309, "distribution": {"name": "U_5.5988012773515985_13.73789130633918", "type": "Empirical"}, "min_duration": 5598.801277351598, "max_duration": 13737.89130633918}, {"first_node": 303, "second_node": 304, "min_duration": 0.0, "max_duration": "inf"}, {"first_node": 305, "second_node": 306, "min_duration": 0.0, "max_duration": "inf"}, {"first_node": 307, "second_node": 308, "min_duration": 0.0, "max_duration": "inf"}, {"first_node": 310, "second_node": 311, "distribution": {"name": "N_77.59074404376514_4.143466031895813", "type": "Empirical"}, "min_duration": "-inf", "max_duration": "inf"}, {"first_node": 312, "second_node": 313, "distribution": {"name": "U_3.3483912379626553_20.506863219523147", "type": "Empirical"}, "min_duration": 3348.3912379626554, "max_duration": 20506.863219523148}, {"first_node": 314, "second_node": 315, "distribution": {"name": "U_4.553154011022241_17.38901359424682", "type": "Empirical"}, "min_duration": 4553.154011022241, "max_duration": 17389.01359424682}, {"first_node": 316, "second_node": 317, "distribution": {"name": "U_6.595445645565224_26.781317096514602", "type": "Empirical"}, "min_duration": 6595.445645565224, "max_duration": 26781.317096514602}, {"first_node": 311, "second_node": 312, "min_duration": 0.0, "max_duration": "inf"}, {"first_node": 313, "second_node": 314, "min_duration": 0.0, "max_duration": "inf"}, {"first_node": 315, "second_node": 316, "min_duration": 0.0, "max_duration": "inf"}, {"first_node": 276, "second_node": 278, "min_duration": 0.0, "max_duration": "inf"}, {"first_node": 284, "second_node": 286, "min_duration": 0.0, "max_duration": "inf"}, {"first_node": 292, "second_node": 294, "min_duration": 0.0, "max_duration": "inf"}, {"first_node": 300, "second_node": 302, "min_duration": 0.0, "max_duration": "inf"}, {"first_node": 308, "second_node": 310, "min_duration": 0.0, "max_duration": "inf"}, {"first_node": 318, "second_node": 319, "distribution": {"name": "N_128.4834611802108_3.357526482679346", "type": "Empirical"}, "min_duration": "-inf", "max_duration": "inf"}, {"first_node": 320, "second_node": 321, "distribution": {"name": "U_6.487635500639044_9.622984527604231", "type": "Empirical"}, "min_duration": 6487.635500639044, "max_duration": 9622.98452760423}, {"first_node": 316, "second_node": 318, "min_duration": 0.0, "max_duration": "inf"}, {"first_node": 319, "second_node": 320, "min_duration": 0.0, "max_duration": "inf"}, {"first_node": 60, "second_node": 270, "min_duration": 0.0, "max_duration": "inf"}, {"first_node": 321, "second_node": 61, "min_duration": 0.0, "max_duration": "inf"}, {"first_node": 59, "second_node": 80, "min_duration": 0.0, "max_duration": 2417.390971085931}, {"first_node": 81, "second_node": 100, "min_duration": 0.0, "max_duration": 3751.8149868661876}, {"first_node": 101, "second_node": 112, "min_duration": 0.0, "max_duration": 4521.780779108103}, {"first_node": 113, "second_node": 172, "min_duration": 0.0, "max_duration": 4552.356646925889}, {"first_node": 173, "second_node": 240, "min_duration": 0.0, "max_duration": 4604.699572532654}, {"first_node": 241, "second_node": 268, "min_duration": 0.0, "max_duration": 4023.4873832244975}, {"first_node": 269, "second_node": 320, "min_duration": 0.0, "max_duration": 3033.405845612947}, {"first_node": 60, "second_node": 58, "min_duration": 1060646.117010896, "max_duration": "inf"}, {"first_node": 60, "second_node": 321, "min_duration": 0.0, "max_duration": 1441505.6510338103}], "num_agents": 1}